ye3sld/__init__.py
ye3sld/ye3sld.py
ye3sld-1.0.4.dist-info/METADATA
ye3sld-1.0.4.dist-info/WHEEL
ye3sld-1.0.4.dist-info/entry_points.txt
ye3sld-1.0.4.dist-info/licenses/LICENSE
ye3sld-1.0.4.dist-info/RECORD
