Metadata-Version: 2.4
Name: ye3sld
Version: 1.0.4
Summary: Create an html file that shows the directory listing structure of an s3 bucket.
Project-URL: Homepage, https://github.com/palw3ey/ye3sld
Project-URL: Documentation, https://github.com/palw3ey/ye3sld
Project-URL: Repository, https://github.com/palw3ey/ye3sld.git
Author-email: palw3ey <palw3ey@gmail.com>
Maintainer-email: palw3ey <palw3ey@gmail.com>
License: MIT License
License-File: LICENSE
Keywords: bucket,directory,html,s3,tree
Classifier: Development Status :: 5 - Production/Stable
Classifier: Intended Audience :: Developers
Classifier: License :: OSI Approved :: MIT License
Classifier: Operating System :: OS Independent
Classifier: Programming Language :: Python :: 3.8
Requires-Python: >=3.8
Requires-Dist: boto3
